ANNOUNCE
AUTHORS
CHANGES
FAQ
INSTALL
LICENSE
MANIFEST.in
README
THANKS
TODO
ez_setup.py
setup.py
PhyloSequel.egg-info/PKG-INFO
PhyloSequel.egg-info/SOURCES.txt
PhyloSequel.egg-info/dependency_links.txt
PhyloSequel.egg-info/requires.txt
PhyloSequel.egg-info/top_level.txt
PhyloSequel.egg-info/zip-safe
phylosequel/__init__.py
phylosequel/biosql.py
scripts/phylosql-gettree.py
scripts/phylosql-insert.py