Metadata-Version: 1.0
Name: PhyloSequel
Version: 0.0.2
Summary: Toolkit and library for BioSQL database interaction and operations.
Home-page: http://jeetworks.org/
Author: Jeet Sukumaran
Author-email: jeetsukumaran@gmail.com
License: LGPL 3+
Keywords: phylogenetics evolution biology SQL database
Platform: UNKNOWN
Classifier: Environment :: Console
Classifier: Intended Audience :: Developers
Classifier: Intended Audience :: Science/Research
Classifier: License :: OSI Approved :: GNU Library or Lesser General Public License (LGPL)
Classifier: Natural Language :: English
Classifier: Operating System :: OS Independent
Classifier: Programming Language :: Python
Classifier: Topic :: Scientific/Engineering :: Bio-Informatics
Classifier: Topic :: Database :: Front-Ends
